nullity/__init__.py
nullity/matrix.py
nullity-0.0.5.dist-info/LICENSE
nullity-0.0.5.dist-info/METADATA
nullity-0.0.5.dist-info/WHEEL
nullity-0.0.5.dist-info/top_level.txt
nullity-0.0.5.dist-info/RECORD
