Metadata-Version: 2.1
Name: nullity
Version: 0.0.5
Summary: A package for all things linear algebra
Home-page: https://github.com/mihiraggarwal/nullity
Author: Mihir Aggarwal
Author-email: mail@mihiraggarwal.me
Keywords: linear,algebra,linear algebra,linalg,lin-alg,linearalgebra,eigen,eigenvalue,eigenvector,nullity,null,null space,rank nullity
Classifier: Programming Language :: Python :: 3
Classifier: Operating System :: OS Independent
License-File: LICENSE
Requires-Dist: numpy
